{
    "about": "Giới thiệu",
    "articles": "công thức",
    "home": "Thức ăn đề xuất",
    "slogan": "Nhà ăn trực tuyến của Jlice, hướng dẫn công thức món ăn Trung Quốc.",
    "hot": "công thức cổ điển",
    "desc": "12 giờ đêm, chuông reo và thời gian của một căng tin ở một góc thành phố bắt đầu. Đây là công thức món ăn Trung Quốc của căng tin Jlice. Chỉ có thức ăn và tình yêu là không thể bỏ qua.",
    "info": "Dưới đây là công thức nấu ăn cổ điển của Trung Quốc. Thích hợp cho người mới bắt đầu, cũng có hướng dẫn công thức nâng cao."
}